dataanalysis/__init__.py
dataanalysis/analysisfactory.py
dataanalysis/bcolors.py
dataanalysis/callback.py
dataanalysis/context.py
dataanalysis/core.py
dataanalysis/ddservice.py
dataanalysis/displaygraph.py
dataanalysis/emerge.py
dataanalysis/graphtools.py
dataanalysis/hashdot.py
dataanalysis/hashtools.py
dataanalysis/importing.py
dataanalysis/jsonify.py
dataanalysis/nodetools.py
dataanalysis/printhook.py
dataanalysis/rundda.py
dataanalysis/caches/__init__.py
dataanalysis/caches/backends.py
dataanalysis/caches/cache_core.py
dataanalysis/caches/delegating.py
dataanalysis/caches/queue.py
dataanalysis/caches/resources.py
dataanalysis/caches/sql.py
data_analysis-1.1.43.dist-info/COPYING
data_analysis-1.1.43.dist-info/METADATA
data_analysis-1.1.43.dist-info/WHEEL
data_analysis-1.1.43.dist-info/entry_points.txt
data_analysis-1.1.43.dist-info/top_level.txt
data_analysis-1.1.43.dist-info/RECORD
