Metadata-Version: 2.1
Name: data-analysis
Version: 1.1.43
Summary: UNKNOWN
Home-page: https://odahub.io/
Author: V.S.
Author-email: vladimir.savchenko@gmail.com
License: 'Creative Commons Attribution-Noncommercial-Share Alike license',
Platform: UNKNOWN
Classifier: Development Status :: 4 - Beta
Classifier: Environment :: Console
Classifier: Intended Audience :: Science/Research
Classifier: License :: OSI Approved :: GNU General Public License v2 or later (GPLv2+)
Classifier: Operating System :: POSIX
Classifier: Programming Language :: Python :: 2.7
Classifier: Programming Language :: Python :: 3.4
Classifier: Programming Language :: Python :: 3.5
Classifier: Programming Language :: Python :: 3.6
Classifier: Programming Language :: Python :: 3.7
Classifier: Topic :: Internet
Classifier: Topic :: Scientific/Engineering
License-File: COPYING
Requires-Dist: lxml
Requires-Dist: six
Requires-Dist: coloredlogs
Requires-Dist: path.py
Requires-Dist: minio
Requires-Dist: rdflib
Requires-Dist: keyring
Requires-Dist: keyrings.cryptfile
Requires-Dist: rdflib-jsonld
Requires-Dist: healpy
Requires-Dist: scipy
Requires-Dist: pydot
Requires-Dist: numpy
Requires-Dist: pandas
Requires-Dist: astropy
Requires-Dist: persist-queue
Requires-Dist: flask
Requires-Dist: flask-restful
Requires-Dist: pytest
Requires-Dist: pytest-flask
Requires-Dist: psutil
Requires-Dist: logstash-formatter
Requires-Dist: requests
Requires-Dist: PyYAML (>=5.1)
Requires-Dist: oda-node (>=0.1.36)
Requires-Dist: python-shell-colors
Requires-Dist: future
